JsonQuery/JsonQuery.py
JsonQuery/__init__.py
JsonQuery/errors.py
JsonQuery/module_importer.py
JsonQuery/queries.py
robotframework_jsonquery-1.0.3.dist-info/LICENSE
robotframework_jsonquery-1.0.3.dist-info/METADATA
robotframework_jsonquery-1.0.3.dist-info/WHEEL
robotframework_jsonquery-1.0.3.dist-info/RECORD
