Metadata-Version: 2.1
Name: robotframework-jsonquery
Version: 1.0.3
Summary: Robot Framework library for parsing json files
Home-page: https://github.com/otemek/robotframework-jsonquery
License: MIT
Author: tom bsc
Author-email: etombsc@gmail.com
Requires-Python: >=3.9,<4.0
Classifier: Framework :: Robot Framework :: Library
Classifier: Framework :: Robot Framework :: Tool
Classifier: License :: OSI Approved :: MIT License
Classifier: Programming Language :: Python :: 3
Classifier: Programming Language :: Python :: 3.9
Classifier: Programming Language :: Python :: 3.10
Classifier: Programming Language :: Python :: 3.11
Requires-Dist: jmespath (<2)
Requires-Dist: jsonpath_ng (<2)
Requires-Dist: robotframework
Project-URL: Documentation, https://otemek.github.io/robotframework-jsonquery/JsonQuery.html
Project-URL: Repository, https://github.com/otemek/robotframework-jsonquery
